{
  "success": true,
  "data": [
    {
      "id": 3,
      "title": "勤劳的嘉奖",
      "desc": "题目/勤劳的嘉奖 文/将晚的天 灰兔爸爸对灰兔哥和灰兔妹的懒深恶痛嫉。 他无时无刻不在寻找机会教育他们。 今天难得的一家人都有空，就相约一起去超...",
      "imgUrl": "//upload-images.jianshu.io/upload_images/12118808-9377e54d6c870296.jpg?imageMogr2/auto-orient/strip|imageView2/1/w/300/h/240"
    },
    {
      "id": 4,
      "title": "童话｜勤劳的嘉奖",
      "desc": "题目/勤劳的嘉奖 文/将晚的天 灰兔爸爸对灰兔哥和灰兔妹的懒深恶痛嫉。 他无时无刻不在寻找机会教育他们。 今天难得的一家人都有空，就相约一起去超...",
      "imgUrl": "//upload-images.jianshu.io/upload_images/12118808-9377e54d6c870296.jpg?imageMogr2/auto-orient/strip|imageView2/1/w/300/h/240"
    },
    {
      "id": 5,
      "title": "童话｜勤劳的嘉奖",
      "desc": "题目/勤劳的嘉奖 文/将晚的天 灰兔爸爸对灰兔哥和灰兔妹的懒深恶痛嫉。 他无时无刻不在寻找机会教育他们。 今天难得的一家人都有空，就相约一起去超...",
      "imgUrl": "//upload-images.jianshu.io/upload_images/12118808-9377e54d6c870296.jpg?imageMogr2/auto-orient/strip|imageView2/1/w/300/h/240"
    },
    {
      "id": 6,
      "title": "童话｜勤劳的嘉奖",
      "desc": "题目/勤劳的嘉奖 文/将晚的天 灰兔爸爸对灰兔哥和灰兔妹的懒深恶痛嫉。 他无时无刻不在寻找机会教育他们。 今天难得的一家人都有空，就相约一起去超...",
      "imgUrl": "//upload-images.jianshu.io/upload_images/12118808-9377e54d6c870296.jpg?imageMogr2/auto-orient/strip|imageView2/1/w/300/h/240"
    },
    {
      "id": 7,
      "title": "童话｜勤劳的嘉奖",
      "desc": "题目/勤劳的嘉奖 文/将晚的天 灰兔爸爸对灰兔哥和灰兔妹的懒深恶痛嫉。 他无时无刻不在寻找机会教育他们。 今天难得的一家人都有空，就相约一起去超...",
      "imgUrl": "//upload-images.jianshu.io/upload_images/12118808-9377e54d6c870296.jpg?imageMogr2/auto-orient/strip|imageView2/1/w/300/h/240"
    }
  ]
}